{
  "_class": "shapePath",
  "booleanOperation": -1,
  "do_objectID": "6399EC1E-27D7-4B14-AE81-011361E7A3BC",
  "edited": true,
  "exportOptions": {
    "_class": "exportOptions",
    "exportFormats": [
    ],
    "includedLayerIds": [
    ],
    "layerOptions": 0,
    "shouldTrim": false
  },
  "frame": {
    "_class": "rect",
    "constrainProportions": false,
    "height": 3,
    "width": 504,
    "x": 0,
    "y": 0
  },
  "isFlippedHorizontal": false,
  "isFlippedVertical": false,
  "isLocked": false,
  "isVisible": true,
  "layerListExpandedType": 0,
  "name": "Path",
  "nameIsFixed": false,
  "path": {
    "_class": "path",
    "isClosed": false,
    "pointRadiusBehaviour": 1,
    "points": [
      {
        "_class": "curvePoint",
        "cornerRadius": 0,
        "curveFrom": "{0.20634920634920631, 0.66666666666666663}",
        "curveMode": 1,
        "curveTo": "{0.20634920634920631, 0.66666666666666663}",
        "hasCurveFrom": false,
        "hasCurveTo": false,
        "point": "{0.0009605073777706702, 0.50000000000002054}"
      },
      {
        "_class": "curvePoint",
        "cornerRadius": 0,
        "curveFrom": "{0.20833333333333331, 1}",
        "curveMode": 1,
        "curveTo": "{0.20833333333333331, 1}",
        "hasCurveFrom": false,
        "hasCurveTo": false,
        "point": "{0.99901041666279156, 0.5}"
      }
    ]
  },
  "resizingConstraint": 63,
  "resizingType": 0,
  "rotation": 0,
  "shouldBreakMaskChain": false
}