{
  "_class": "shapePath",
  "booleanOperation": -1,
  "do_objectID": "5873CBAE-C402-4D86-B513-B8684D21D2B7",
  "edited": true,
  "exportOptions": {
    "_class": "exportOptions",
    "exportFormats": [
    ],
    "includedLayerIds": [
    ],
    "layerOptions": 0,
    "shouldTrim": false
  },
  "frame": {
    "_class": "rect",
    "constrainProportions": false,
    "height": 22.00000000000002,
    "width": 35,
    "x": 0,
    "y": 0
  },
  "isFlippedHorizontal": false,
  "isFlippedVertical": false,
  "isLocked": false,
  "isVisible": true,
  "layerListExpandedType": 0,
  "name": "Path",
  "nameIsFixed": false,
  "path": {
    "_class": "path",
    "isClosed": false,
    "pointRadiusBehaviour": 1,
    "points": [
      {
        "_class": "curvePoint",
        "cornerRadius": 0,
        "curveFrom": "{0.93982700263256869, 0}",
        "curveMode": 1,
        "curveTo": "{0.93982700263256869, 0}",
        "hasCurveFrom": false,
        "hasCurveTo": false,
        "point": "{0.93982700263256869, 0}"
      },
      {
        "_class": "curvePoint",
        "cornerRadius": 0,
        "curveFrom": "{0, 0.90292237137214237}",
        "curveMode": 1,
        "curveTo": "{0, 0.90292237137214237}",
        "hasCurveFrom": false,
        "hasCurveTo": false,
        "point": "{0, 0.90292237137214237}"
      },
      {
        "_class": "curvePoint",
        "cornerRadius": 0,
        "curveFrom": "{0.058480631816472207, 1}",
        "curveMode": 1,
        "curveTo": "{0.058480631816472207, 1}",
        "hasCurveFrom": false,
        "hasCurveTo": false,
        "point": "{0.058480631816472207, 1}"
      },
      {
        "_class": "curvePoint",
        "cornerRadius": 0,
        "curveFrom": "{1, 0.091453821176313024}",
        "curveMode": 1,
        "curveTo": "{1, 0.091453821176313024}",
        "hasCurveFrom": false,
        "hasCurveTo": false,
        "point": "{1, 0.091453821176313024}"
      },
      {
        "_class": "curvePoint",
        "cornerRadius": 0,
        "curveFrom": "{0.93982700263256869, 0}",
        "curveMode": 1,
        "curveTo": "{0.93982700263256869, 0}",
        "hasCurveFrom": false,
        "hasCurveTo": false,
        "point": "{0.93982700263256869, 0}"
      }
    ]
  },
  "resizingConstraint": 63,
  "resizingType": 0,
  "rotation": 0,
  "shouldBreakMaskChain": false
}